score_calculator/__init__.py
score_calculator/sf12_score.py
score_calculator/sf12_utils.py
score_calculator-1.1.0.dist-info/LICENSE.md
score_calculator-1.1.0.dist-info/METADATA
score_calculator-1.1.0.dist-info/WHEEL
score_calculator-1.1.0.dist-info/RECORD
