Metadata-Version: 2.1
Name: score_calculator
Version: 1.1.0
Summary: This is a python library to calculate  12-item Short Form Survey (SF-12) score.
Author: Luís Bastião Silva
Author-email: luis.kop@gmail.com
Requires-Python: >=3.12,<4.0
Classifier: License :: OSI Approved :: BSD License
Classifier: Operating System :: OS Independent
Classifier: Programming Language :: Python :: 3
Classifier: Programming Language :: Python :: 3.12
Requires-Dist: numpy (>=1.26.4,<2.0.0)
Requires-Dist: pandas (>=2.2.0,<3.0.0)
Requires-Dist: pytest (>=8.3.2,<9.0.0)
Requires-Dist: tabulate (>=0.9.0,<0.10.0)
